{
  "OOAK-s": "Platform",
  "OOAK-e": "Busway",
  "OMAL-n": "Platform",
  "OMAL-m": "Lobby",
  "ONST-m": "CR Exit",
  "OCHN-m": "Lobby",
  "OCHS-m": "Lobby",
  "OFOR-n": "Platform",
  "OFOR-m": "Main Lobby",
  "SSOU-w": "Arrival Platform",
  "RJFK-n": "Braintree NB",
  "RJFK-s": "Braintree SB",
  "RJFK-e": "Ashmont NB",
  "RJFK-w": "Ashmont SB",
  "SEAV-e": "Outbound",
  "SEAV-w": "Inbound",
  "SBOX-e": "Outbound",
  "SBOX-w": "Inbound",
  "SBSQ-e": "Outbound",
  "SBSQ-w": "Inbound",
  "SCHS-w": "Inbound",
  "GCOS-w": "Track 1",
  "GCOS-e": "Track 2",
  "GBSS-w": "Copley & West",
  "GBSS-e": "Medford/Tufts",
  "GMSS-w": "Copley & West",
  "GMSS-e": "Medford/Tufts",
  "GGSS-w": "Copley & West",
  "GGSS-e": "Medford/Tufts",
  "GESS-w": "Copley & West",
  "GESS-e": "Medford/Tufts",
  "GUNS-e": "Track 1",
  "GUNS-w": "Track 2",
  "GLEC-e": "Union Sq",
  "GLEC-w": "Copley & West",
  "GNST-m": "CR Exit",
  "GRPKE-m": "Winter St Concourse",
  "GRPKW-n": "Fence Track",
  "GRPKW-w": "Wall Track",
  "GKEN-n": "C/D East",
  "GKEN-s": "C/D West",
  "GKEN-e": "B East",
  "GKEN-w": "B West",
  "GRIV-w": "Entire Station",
  "SDUD-n": "Platform F",
  "SDUD-s": "Platform C",
  "SDUD-e": "Platform D",
  "SDUD-w": "Platform A",
  "SDUD-c": "Platform E (East)",
  "SDUD-m": "Platform E (West)",
  "SLEC-m": "Inner Platform",
  "SLEC-c": "Outer Platform",
  "SHAR-n": "Upper",
  "SHAR-m": "Lower",
  "MMAT-n": "South",
  "MMAT-s": "North",
  "SDAV-m": "Busway",
  "SFOR-n": "Upper (Fence)",
  "SFOR-s": "Upper (Island)",
  "RBRA-n": "Busway"
}
